EscrowAICI/EscrowAI.py
EscrowAICI/__init__.py
EscrowAICI/algo_owner.py
EscrowAICI/checks.py
EscrowAICI/encryption.py
EscrowAICI/general.py
EscrowAICI/main.py
EscrowAICI/utils.py
escrowaici-0.1.8.dist-info/METADATA
escrowaici-0.1.8.dist-info/WHEEL
escrowaici-0.1.8.dist-info/entry_points.txt
escrowaici-0.1.8.dist-info/top_level.txt
escrowaici-0.1.8.dist-info/RECORD
