Metadata-Version: 2.4
Name: EscrowAICI
Version: 0.1.8
Summary: Expose Escrow AI workflows to CICD pipelines
Home-page: https://github.com/BeekeeperAI/bk-escrowai-ci-sdk
Author: Beekeeper AI
Author-email: engineering@beekeeperai.com
Classifier: Development Status :: 4 - Beta
Classifier: Intended Audience :: Developers
Classifier: License :: OSI Approved :: MIT License
Classifier: Programming Language :: Python :: 3
Classifier: Programming Language :: Python :: 3.8
Requires-Python: >=3.6
Requires-Dist: pyJWT
Requires-Dist: requests
Requires-Dist: azure-storage-blob>=12.22.0
Requires-Dist: sseclient
Requires-Dist: cryptography==44.0.1
Requires-Dist: pyyaml
Requires-Dist: gitpython
Dynamic: author
Dynamic: author-email
Dynamic: classifier
Dynamic: description
Dynamic: description-content-type
Dynamic: home-page
Dynamic: requires-dist
Dynamic: requires-python
Dynamic: summary
